MANIFEST.in
README.txt
requirements.txt
setup.cfg
setup.py
probes/__init__.py
probes/collector.py
probes/config.py
probes/pinger.py
probes/server.py
probes/tester.py
probes.egg-info/PKG-INFO
probes.egg-info/SOURCES.txt
probes.egg-info/dependency_links.txt
probes.egg-info/requires.txt
probes.egg-info/top_level.txt